Metadata-Version: 2.1
Name: XGBfnc
Version: 0.1.5
Summary: Flat, node classification model
Home-page: https://github.com/migueleci/XGBfnc
Author: Miguel Romero
Author-email: romeromiguelin@gmail.com
License: MIT
Platform: UNKNOWN
Classifier: Development Status :: 1 - Planning
Classifier: Intended Audience :: Science/Research
Classifier: License :: OSI Approved :: BSD License
Classifier: Operating System :: POSIX :: Linux
Classifier: Programming Language :: Python :: 3
Classifier: Programming Language :: Python :: 3.6
License-File: LICENSE
